deal/__init__.py
deal/cast.py
deal/config.py
deal/exceptions.py
py_deal-0.1.0.dist-info/METADATA
py_deal-0.1.0.dist-info/WHEEL
py_deal-0.1.0.dist-info/licenses/LICENSE
py_deal-0.1.0.dist-info/RECORD
