Metadata-Version: 2.4
Name: py-deal
Version: 0.1.0
Summary: Simple .env-to-dataclass validator and static config holder
Project-URL: Homepage, https://github.com/kundlatsch/py_deal
Project-URL: Repository, https://github.com/kundlatsch/py_deal
Project-URL: Issues, https://github.com/kundlatsch/py_deal/issues
Author-email: kundlatsch <gustavo.kundlatsch@gmail.com>
License-Expression: MIT
License-File: LICENSE
Requires-Python: >=3.9
Requires-Dist: python-dotenv>=1.0.0
Provides-Extra: test
Requires-Dist: pytest>=7.0.0; extra == 'test'
